lyft_bikes/__init__.py
lyft_bikes/bikes.py
lyft_bikes/geo/__init__.py
lyft_bikes/geo/fees.geojson
lyft_bikes/historical/__init__.py
lyft_bikes/historical/dates.py
lyft_bikes/historical/downloader.py
lyft_bikes/historical/historical.py
lyft_bikes/live.py
lyft_bikes/pricing.py
lyft_bikes/py.typed
lyft_bikes/stations.py
lyft_bikes-0.1.3.dist-info/LICENSE
lyft_bikes-0.1.3.dist-info/METADATA
lyft_bikes-0.1.3.dist-info/WHEEL
lyft_bikes-0.1.3.dist-info/RECORD
