Metadata-Version: 2.1
Name: lyft-bikes
Version: 0.1.3
Summary: Python Client for Lyft Bike Sharing Data.
Home-page: https://wd60622.github.io/lyft-bikes/
License: MIT
Author: Will Dean
Author-email: wd60622@gmail.com
Requires-Python: >=3.8,<4.0
Classifier: Intended Audience :: Developers
Classifier: Intended Audience :: Science/Research
Classifier: License :: OSI Approved :: MIT License
Classifier: Operating System :: MacOS
Classifier: Operating System :: Microsoft :: Windows
Classifier: Operating System :: POSIX
Classifier: Operating System :: POSIX :: Linux
Classifier: Operating System :: Unix
Classifier: Programming Language :: Python :: 3
Classifier: Programming Language :: Python :: 3.8
Classifier: Programming Language :: Python :: 3.9
Classifier: Programming Language :: Python :: 3.10
Classifier: Programming Language :: Python :: 3.11
Classifier: Programming Language :: Python :: 3.12
Classifier: Topic :: Scientific/Engineering
Classifier: Topic :: Software Development :: Libraries
Provides-Extra: boundary
Requires-Dist: geopandas ; extra == "boundary"
Requires-Dist: pandas
Requires-Dist: requests
Project-URL: Documentation, https://wd60622.github.io/lyft-bikes/
Project-URL: Repository, https://github.com/wd60622/lyft-bikes/
